i3ipct/__init__.py
i3ipct/find.py
i3ipct/focus.py
i3ipct-0.1.dist-info/LICENSE
i3ipct-0.1.dist-info/METADATA
i3ipct-0.1.dist-info/WHEEL
i3ipct-0.1.dist-info/top_level.txt
i3ipct-0.1.dist-info/RECORD
