Metadata-Version: 2.1
Name: i3ipct
Version: 0.1
Summary: Tools build up on i3ipc (focus, find in tree)
Home-page: https://github.com/bschnitz/i3ipc-python-tools
Author: Benjamin Schnitzler
Author-email: regenbogenbauer@web.de
License: UNKNOWN
Platform: UNKNOWN
Classifier: Programming Language :: Python :: 3
Classifier: License :: OSI Approved :: BSD License
Requires-Dist: i3ipc
